Metadata-Version: 2.1
Name: SimplePy2Exe
Version: 0.1.4
Summary: Transforme seu projeto Python em um executável
Home-page: https://github.com/hqr90/py2exe
Author: Hilton Queiroz Rebello
Author-email: rebello.hiltonqueiroz@gmail.com
Classifier: Programming Language :: Python :: 3
Classifier: License :: OSI Approved :: MIT License
Classifier: Operating System :: OS Independent
Requires-Python: >=3.8
License-File: LICENCE
Requires-Dist: altgraph
Requires-Dist: packaging
Requires-Dist: pefile
Requires-Dist: pillow
Requires-Dist: pyinstaller
Requires-Dist: pyinstaller-hooks-contrib
Requires-Dist: PyQt5
Requires-Dist: pywin32-ctypes
